pipelens/__init__.py
pipelens/chart.py
pipelens/decorator.py
pipelens/extension/__init__.py
pipelens/extension/llm_track.py
pipelens/pipeline.py
pipelens/pipeline_types.py
pipelens/step.py
pipelens/transport/__init__.py
pipelens/transport/base_transport.py
pipelens/transport/http_transport.py
pipelens-1.13.0.dist-info/METADATA
pipelens-1.13.0.dist-info/WHEEL
pipelens-1.13.0.dist-info/RECORD
