Metadata-Version: 2.4
Name: pipelens
Version: 1.13.0
Summary: An observability tool built to track, inspect and visualize intermediate steps in a pipeline, allowing user to easily debug or analyze through a dashboard.
License: MIT
Keywords: pipelens,pipeline,lens,observability,monitoring,rag,llm,visualization,tracing,tracking,debugging,analytics,performance,metrics
Author: lokwkin
Author-email: lokwkin@gmail.com
Requires-Python: >=3.12,<4.0
Classifier: License :: OSI Approved :: MIT License
Classifier: Programming Language :: Python :: 3
Classifier: Programming Language :: Python :: 3.12
Classifier: Programming Language :: Python :: 3.13
Classifier: Programming Language :: Python :: 3.14
Requires-Dist: aiohttp (>=3.11.16,<4.0.0)
Requires-Dist: pydantic (>=2.11.3,<3.0.0)
Requires-Dist: pyee (>=13.0.0,<14.0.0)
Requires-Dist: requests (>=2.32.3,<3.0.0)
Project-URL: Homepage, https://github.com/lokwkin/pipelens
Project-URL: Repository, https://github.com/lokwkin/pipelens
